Workbook

Sheet Итоговый лист
A1: Доходы | D1: Расходы | H1: Примечание
A2: Входные билеты | C2: 52500 | D2: Промоутеры | F2: =Промоутеры!F14 -> 50500 | H2: Долг безнал: | I2: Долг нал:
A3: Бар | C3: 35560 | D3: Такси | F3: ='Лист выплат'!D70 -> 0 | H3: Д3 Даша-2300 | I3: Д3 Даша-6750
A4: Консумация Бара | C4: 83500 | D4: Промо | F4: ='Лист выплат'!G68 -> 8000 | H4: Д5 Софья-22000 | I4: Д5 Софья-500
A5: Консумация кухни | D5: Ставка менеджера | F5: ='Лист выплат'!D59 -> 4000 | H5: Д9 Лилит-8850 | I5: Д9 Лилит-2500
A6: Crazy Menu | C6: 239500 | D6: Ставка танцовщиц | F6: =SUM('Лист выплат'!D3:D17) -> 7500 | H6: Д11 Дана-18300 | I6: Д11 Дана-6250
A7: Общий чай | C7: 96000 | D7: Ставка хостес | F7: =SUM('Лист выплат'!D39:D43) -> 8000 | H7: Д18 Аннет-34200 | I7: Д18 Аннет-500
A8: Overtime | D8: Ставка официантов | F8: =SUM('Лист выплат'!D30:D37) -> 3000 | H8: Д21 Банни-1250 | I8: Д21 Банни-8250
A9: Кальяны | C9: 46000 | D9: Ставка бармена | F9: =SUM('Лист выплат'!D52:D55) -> 7000 | H9: Д66 Алиса-29700 | I9: Д66 Алиса-2850
A10: Шары | D10: Ставка патигерл | F10: =SUM('Лист выплат'!D19:D28) -> 0 | H10: Оф3 Каталина-1050 | I10: Оф3 Каталина-400
A11: Штрафы | D11: Выплата админа | F11: =SUM('Лист выплат'!D60:D61) -> 15000 | H11: Оф4 Ника-750 | I11: Оф4 Ника-4400
A12: Стафф | D12: Выплата стажерам | F12: =SUM('Лист выплат'!D45:D51) -> 0 | H12: Н3 Влада-1000 | I12: Н4 Тати-3000
A13: Стафф кальян | D13: Выплата СБ | F13: =SUM('Лист выплат'!D64:D66) -> 12000 | H13: Н4 Тати-1500 | I13: Б4 Камила-4000
A14: Доход клуба | C14: 22800 | D14: CRZ - меню | F14: ='Лист выплат'!H68 -> 108600 | H14: Б4 Камила-1600 | I14: Б52 Даня-4000
A15: Сервисный сбор | C15: 12110 | D15: Консумация | F15: ='Лист выплат'!I68 -> 21900 | H15: Б52 Даня-3000 | I15: К21 Маратик-7700
A16: Итого | C16: =SUM(C2:C15) -> 587970 | D16: Чаевые | F16: ='Лист выплат'!J68 -> 68450 | H16: К21 Маратик-4700 | I16: Дж14 Сергей-4200
A17: плюс по кассе | C17: 0 | D17: Ставка кальянщика | F17: =SUM('Лист выплат'!D56:D57) -> 0 | H17: Дж14 Сергей-3000 | I17: А17 Юля-16700
A18: Итого за смену | C18: =SUM(C16:C17) -> 587970 | D18: Ставка диджея | F18: ='Лист выплат'!D58 -> 3000 | H18: М69 Марина-5850 | I18: СБ Женя Егоров-350
D19: Уборщица | F19: =SUM('Лист выплат'!D67) -> 2000 | H19: А17 Юля-14850 | I19: СБ Дима Песков-350
D20: Стилист/визажист | F20: ='Лист выплат'!D74 -> 1000 | H20: СБ Женя Егоров-2950 | I20: СБ Денис Ермаков-300
A21: Входные билеты | D21: % таксистам | F21: ='Лист выплат'!D71 -> 0 | H21: СБ Дима Песков-2900 | I21: Стилист Зарема-500
A22: цена | B22: кол-во | C22: сумма | D22: Прочие расходы | F22: ='Лист выплат'!D72 -> 0 | H22: СБ Денис Ермаков-3000 | I22: Визажист Оксана-500
A23: Бесплатно | B23: 4 | D23: 5% Р9 | F23: ='Лист выплат'!D73 -> 300 | H23: Р1 Дима-2500 | I23: Р1 Дима-13000
A24: 1000 | D24: 5% со столов | F24: ='Лист выплат'!F68 -> 5950 | H24: Р15 Гриша-1000 | I24: Р9 Рома-5000
A25: 1500 | B25: 7 | C25: 10500 | D25: 5% промоутеров | F25: =SUM('Лист выплат'!D75) -> 11100 | H25: Р17 Ильяз-3500 | I25: Р10 Дима-1000
A26: 2000 | B26: 18 | C26: 36000 | D26: % Жени | F26: =SUM('Лист выплат'!D76) -> 0 | H26: ИТОГО: 169750 | I26: Р15 Гриша-10000
A27: 3000 | B27: 2 | C27: 6000 | D27: Ставка ЛМ | F27: =SUM('Лист выплат'!D62:D63) -> 0 | I27: Р17 Ильяз-20500
A28: 4000 | D28: 5% ЛМ | F28: ='Лист выплат'!E68 -> 0 | I28: Р29 Сергей-1000
A29: 5000 | D29: Итого | F29: =SUM(F2:F28) -> 337300 | I29: %Р1-2750
I30: %Р15-3250
A31: ИТОГО: | B31: =SUM(B23:B30) -> 31 | C31: =SUM(C24:C30) -> 52500 | D31: Инкассация | I31: %Р9-300
E32: кол-во | F32: курс | G32: сумма | I32: %Р17-5100
A33: Наличные | C33: 125550 | D33: Рубль | G33: 86900 | I33: ИТОГО: 135900
A34: Сбербанк | C34: 303580 | D34: Доллар | E34: 100 | F34: 70 | G34: 7000
A35: СБП Сбербанк | C35: 158840 | D35: Евро
A36: Банк Тинькофф
A37: СБП Тинькофф
A40: ИТОГО КАССА: | C40: 500590
A41: ИТОГО: | C41: =SUM(C33:C39) -> 587970 | D41: Итого | G41: =SUM(G33:G40) -> 93900
A42: статистика персонала | H42: итого
A43: Танцовщица | C43: 7 | D43: Долг нал общ | E43: =SUM('Лист выплат'!N79) -> 135900 | I43: Доход | J43: Расход | K43: Чистая прибыль
A44: Официанты | C44: 2 | D44: Долг БН | E44: =SUM('Лист выплат'!M68) -> 169750 | H44: Наличные | I44: =C33 -> 125550 | J44: =SUM(F29-E44) -> 167550 | K44: =SUM(I44-J44) -> -42000
A45: Хостес | C45: 2 | D45: Итого | E45: =SUM(E43:E44) -> 305650 | H45: Б/Н | I45: =SUM(C34:C39) -> 462420 | J45: =E44 -> 169750 | K45: =SUM(I45-J45) -> 292670
A46: Промоутеры | C46: 6 | H46: Итого | I46: =C18 -> 587970 | J46: =F29 -> 337300 | K46: =SUM(I46-J46) -> 250670

Sheet Лист выплат
A1: № | C1: ФАМИЛИЯ | D1: СТАВКА | E1: 5% ЛМ | F1: 0.05 | G1: ПРОМО | H1: CRAZY MENU | I1: Консумация | J1: ЧАЕВЫЕ | K1: ШТРАФЫ | L1: ИТОГО выплат по смене | M1: ДОЛГ | N1: ДОЛГ НАЛ | O1: к выплате
A2: Танцовщицы
A3: Д | B3: 3 | C3: Даша | D3: 2500 | H3: 5350 | I3: =SUM('крейзи консум новый'!X4:X5) -> 1200 | J3: =SUM('Общий чай'!S3:S4)*0.5 -> 0 | L3: =D3+G3+H3+I3+J3-K3 -> 9050 | M3: 2300 | N3: 6750 | O3: =L3-M3-N3 -> 0
A4: Д | B4: 5 | C4: Софья | H4: =SUM('крейзи консум новый'!C6:C7) -> 16200 | I4: =SUM('крейзи консум новый'!X6:X7) -> 3800 | J4: =SUM('Общий чай'!S5:S6)*0.5 -> 2500 | L4: =D4+G4+H4+I4+J4-K4 -> 22500 | M4: 22000 | N4: 500 | O4: =L4-M4-N4 -> 0
A5: Д | B5: 9 | C5: Лилит | D5: 2500 | H5: =SUM('крейзи консум новый'!C8:C9) -> 8550 | I5: =SUM('крейзи консум новый'!X8:X9) -> 300 | J5: =SUM('Общий чай'!S7:S8)*0.5 -> 0 | L5: =D5+G5+H5+I5+J5-K5 -> 11350 | M5: 8850 | N5: 2500 | O5: =L5-M5-N5 -> 0
A6: Д | B6: 11 | C6: Дана | H6: =SUM('крейзи консум новый'!C10:C11) -> 20450 | I6: =SUM('крейзи консум новый'!X10:X11) -> 600 | J6: =SUM('Общий чай'!S9:S10)*0.5 -> 3500 | L6: =D6+G6+H6+I6+J6-K6 -> 24550 | M6: 18300 | N6: 6250 | O6: =L6-M6-N6 -> 0
A7: Д | B7: 18 | C7: Аннет | H7: =SUM('крейзи консум новый'!C12:C13) -> 34200 | I7: =SUM('крейзи консум новый'!X12:X13) -> 0 | J7: =SUM('Общий чай'!S11:S12)*0.5 -> 500 | L7: =D7+G7+H7+I7+J7-K7 -> 34700 | M7: 34200 | N7: 500 | O7: =L7-M7-N7 -> 0
A8: Д | B8: 21 | C8: Банни | D8: 2500 | H8: =SUM('крейзи консум новый'!C14:C15) -> 0 | I8: 2250 | J8: =SUM('Общий чай'!S12:S13)*0.5 -> 4750 | L8: =D8+G8+H8+I8+J8-K8 -> 9500 | M8: 1250 | N8: 8250 | O8: =L8-M8-N8 -> 0
A9: Д | B9: 66 | C9: Алиса | H9: =SUM('крейзи консум новый'!C16:C17) -> 23850 | I9: 1700 | J9: =SUM('Общий чай'!S15:S16)*0.5 -> 7000 | L9: =D9+G9+H9+I9+J9-K9 -> 32550 | M9: 29700 | N9: 2850 | O9: =L9-M9-N9 -> 0
A10: Д | H10: =SUM('крейзи консум новый'!C18:C19) -> 0 | I10: =SUM('крейзи консум новый'!X18:X19) -> 0 | J10: =SUM('Общий чай'!S17:S18)*0.5 -> 0 | L10: =D10+G10+H10+I10+J10-K10 -> 0 | O10: =L10-M10-N10 -> 0
A11: Д | H11: =SUM('крейзи консум новый'!C20:C21) -> 0 | I11: =SUM('крейзи консум новый'!X20:X21) -> 0 | J11: =SUM('Общий чай'!S19:S20)*0.5 -> 0 | L11: =D11+G11+H11+I11+J11-K11 -> 0 | O11: =L11-M11-N11 -> 0
A12: Д | H12: =SUM('крейзи консум новый'!C22:C23) -> 0 | I12: =SUM('крейзи консум новый'!X22:X23) -> 0 | J12: =SUM('Общий чай'!S21:S22)*0.5 -> 0 | L12: =D12+G12+H12+I12+J12-K12 -> 0 | O12: =L12-M12-N12 -> 0
A13: Д | H13: =SUM('крейзи консум новый'!C24:C25) -> 0 | I13: =SUM('крейзи консум новый'!X24:X25) -> 0 | J13: =SUM('Общий чай'!S23:S24)*0.5 -> 0 | L13: =D13+G13+H13+I13+J13-K13 -> 0 | O13: =L13-M13-N13 -> 0
A14: Д | H14: =SUM('крейзи консум новый'!C26:C27) -> 0 | I14: =SUM('крейзи консум новый'!X26:X27) -> 0 | J14: =SUM('Общий чай'!S25:S26)*0.5 -> 0 | L14: =D14+G14+H14+I14+J14-K14 -> 0 | O14: =L14-M14-N14 -> 0
A15: Д | H15: =SUM('крейзи консум новый'!C28:C29) -> 0 | I15: =SUM('крейзи консум новый'!X28:X29) -> 0 | J15: =SUM('Общий чай'!S27:S28)*0.5 -> 0 | L15: =D15+G15+H15+I15+J15-K15 -> 0 | O15: =L15-M15-N15 -> 0
A16: Д | H16: =SUM('крейзи консум новый'!C30:C31) -> 0 | I16: =SUM('крейзи консум новый'!X30:X31) -> 0 | J16: =SUM('Общий чай'!S29:S30)*0.5 -> 0 | L16: =D16+G16+H16+I16+J16-K16 -> 0 | O16: =L16-M16-N16 -> 0
A17: Д | H17: =SUM('крейзи консум новый'!C32:C33) -> 0 | I17: =SUM('крейзи консум новый'!X32:X33) -> 0 | J17: =SUM('Общий чай'!S31:S32)*0.5 -> 0 | L17: =D17+G17+H17+I17+J17-K17 -> 0 | O17: =L17-M17-N17 -> 0
A18: Патигерл
A19: Г | H19: =SUM('крейзи консум новый'!C35:C36) -> 0 | I19: =SUM('крейзи консум новый'!X35:X36) -> 0 | J19: =SUM('Общий чай'!S34:S35)*0.5 -> 0 | L19: =D19+F19+G19+H19+I19+J19-K19 -> 0 | O19: =L19-M19-N19 -> 0
A20: Г | H20: =SUM('крейзи консум новый'!C37:C38) -> 0 | I20: =SUM('крейзи консум новый'!X37:X38) -> 0 | J20: =SUM('Общий чай'!S36:S37)*0.5 -> 0 | L20: =D20+F20+G20+H20+I20+J20-K20 -> 0 | O20: =L20-M20-N20 -> 0
A21: Г | H21: =SUM('крейзи консум новый'!C39:C40) -> 0 | I21: =SUM('крейзи консум новый'!X39:X40) -> 0 | J21: =SUM('Общий чай'!S38:S39)*0.5 -> 0 | L21: =D21+F21+G21+H21+I21+J21-K21 -> 0 | O21: =L21-M21-N21 -> 0
A22: Г | H22: =SUM('крейзи консум новый'!C41:C42) -> 0 | I22: =SUM('крейзи консум новый'!X41:X42) -> 0 | J22: =SUM('Общий чай'!S40:S41)*0.5 -> 0 | L22: =D22+F22+G22+H22+I22+J22-K22 -> 0 | O22: =L22-M22-N22 -> 0
A23: Г | H23: =SUM('крейзи консум новый'!C43:C44) -> 0 | I23: =SUM('крейзи консум новый'!X43:X44) -> 0 | J23: =SUM('Общий чай'!S42:S43)*0.5 -> 0 | L23: =D23+F23+G23+H23+I23+J23-K23 -> 0 | O23: =L23-M23-N23 -> 0
A24: Г | H24: =SUM('крейзи консум новый'!C45:C46) -> 0 | I24: =SUM('крейзи консум новый'!X45:X46) -> 0 | J24: =SUM('Общий чай'!S44:S45)*0.5 -> 0 | L24: =D24+G24+H24+I24+J24-K24 -> 0 | O24: =L24-M24-N24 -> 0
A25: Г | H25: =SUM('крейзи консум новый'!C47:C48) -> 0 | I25: =SUM('крейзи консум новый'!X47:X48) -> 0 | J25: =SUM('Общий чай'!S46:S47)*0.5 -> 0 | L25: =D25+G25+H25+I25+J25-K25 -> 0 | O25: =L25-M25-N25 -> 0
A26: Г | H26: =SUM('крейзи консум новый'!C49:C50) -> 0 | I26: =SUM('крейзи консум новый'!X49:X50) -> 0 | J26: =SUM('Общий чай'!S48:S49)*0.5 -> 0 | L26: =D26+G26+H26+I26+J26-K26 -> 0 | O26: =L26-M26-N26 -> 0
A27: Г | H27: =SUM('крейзи консум новый'!C51:C52) -> 0 | I27: =SUM('крейзи консум новый'!X51:X52) -> 0 | J27: =SUM('Общий чай'!S50:S51)*0.5 -> 0 | L27: =D27+G27+H27+I27+J27-K27 -> 0 | O27: =L27-M27-N27 -> 0
A28: Г | H28: =SUM('крейзи консум новый'!C53:C54) -> 0 | I28: =SUM('крейзи консум новый'!X53:X54) -> 0 | J28: =SUM('Общий чай'!S52:S53)*0.5 -> 0 | L28: =D28+G28+H28+I28+J28-K28 -> 0 | O28: =L28-M28-N28 -> 0
A29: Официанты
A30: Оф | B30: 3 | C30: Каталина | D30: 1500 | F30: 2400 | H30: =SUM('крейзи консум новый'!C56:C57) -> 0 | I30: 1050 | J30: =SUM('Общий чай'!S55:S56)*0.5 -> 1500 | L30: =SUM(D30:J30)-K30 -> 6450 | M30: 1050 | N30: 400 | O30: =L30-M30-N30 -> 5000
A31: Оф | B31: 4 | C31: Ника | D31: 1500 | F31: 2400 | H31: =SUM('крейзи консум новый'!C58:C59) -> 0 | I31: =SUM('крейзи консум новый'!X58:X59) -> 0 | J31: =SUM('Общий чай'!S57:S58)*0.5 -> 1250 | L31: =SUM(D31:J31)-K31 -> 5150 | M31: 750 | N31: 4400 | O31: =L31-M31-N31 -> 0
A32: Оф | H32: =SUM('крейзи консум новый'!C60:C61) -> 0 | I32: =SUM('крейзи консум новый'!X60:X61) -> 0 | J32: =SUM('Общий чай'!S59:S60)*0.5 -> 0 | L32: =SUM(D32:J32)-K32 -> 0 | O32: =L32-M32-N32 -> 0
A33: Оф | H33: =SUM('крейзи консум новый'!C62:C63) -> 0 | I33: =SUM('крейзи консум новый'!X62:X63) -> 0 | J33: =SUM('Общий чай'!S61:S62)*0.5 -> 0 | L33: =SUM(D33:J33)-K33 -> 0 | O33: =L33-M33-N33 -> 0
A34: Оф | H34: =SUM('крейзи консум новый'!C64:C65) -> 0 | I34: =SUM('крейзи консум новый'!X64:X65) -> 0 | J34: =SUM('Общий чай'!S63:S64)*0.5 -> 0 | L34: =SUM(D34:J34)-K34 -> 0 | O34: =L34-M34-N34 -> 0
A35: Оф | H35: =SUM('крейзи консум новый'!C66:C67) -> 0 | I35: =SUM('крейзи консум новый'!X66:X67) -> 0 | J35: =SUM('Общий чай'!S65:S66)*0.5 -> 0 | L35: =SUM(D35:J35)-K35 -> 0 | O35: =L35-M35-N35 -> 0
A36: Оф | H36: =SUM('крейзи консум новый'!C68:C69) -> 0 | I36: =SUM('крейзи консум новый'!X68:X69) -> 0 | J36: =SUM('Общий чай'!S67:S68)*0.5 -> 0 | L36: =SUM(D36:J36)-K36 -> 0 | O36: =L36-M36-N36 -> 0
A37: Оф | H37: =SUM('крейзи консум новый'!C70:C71) -> 0 | I37: =SUM('крейзи консум новый'!X70:X71) -> 0 | J37: =SUM('Общий чай'!S69:S70)*0.5 -> 0 | L37: =SUM(D37:J37)-K37 -> 0 | O37: =L37-M37-N37 -> 0
A38: Хостес
A39: Н | B39: 3 | C39: Влада | D39: 4000 | H39: =SUM('крейзи консум новый'!C73:C74) -> 0 | I39: =SUM('крейзи консум новый'!X73:X74) -> 0 | J39: =SUM('Общий чай'!S72:S73) -> 1000 | L39: =D39+G39+H39+I39+J39-K39 -> 5000 | M39: 1000 | O39: =L39-M39-N39 -> 4000
A40: Н | B40: 4 | C40: Тати | D40: 4000 | H40: =SUM('крейзи консум новый'!C75:C76) -> 0 | I40: =SUM('крейзи консум новый'!X75:X76) -> 0 | J40: =SUM('Общий чай'!S74:S75) -> 1500 | L40: =D40+G40+H40+I40+J40-K40 -> 5500 | M40: 1500 | N40: 3000 | O40: =L40-M40-N40 -> 1000
A41: Н | H41: =SUM('крейзи консум новый'!C77:C78) -> 0 | I41: =SUM('крейзи консум новый'!X77:X78) -> 0 | J41: =SUM('Общий чай'!S76:S77) -> 0 | L41: =D41+G41+H41+I41+J41-K41 -> 0 | O41: =L41-M41-N41 -> 0
A42: Н | H42: =SUM('крейзи консум новый'!C79:C80) -> 0 | I42: =SUM('крейзи консум новый'!X79:X80) -> 0 | J42: =SUM('Общий чай'!S78:S79) -> 0 | L42: =D42+G42+H42+I42+J42-K42 -> 0 | O42: =L42-M42-N42 -> 0
A43: Н | H43: =SUM('крейзи консум новый'!C81:C82) -> 0 | I43: =SUM('крейзи консум новый'!X81:X82) -> 0 | J43: =SUM('Общий чай'!S80:S81) -> 0 | L43: =D43+G43+H43+I43+J43-K43 -> 0 | O43: =L43-M43-N43 -> 0
A44: Стажеры
H45: =SUM('крейзи консум новый'!C84:C85) -> 0 | I45: =SUM('крейзи консум новый'!X84:X85) -> 0 | J45: =SUM('Общий чай'!S83:S84)*0.5 -> 0 | L45: =D45+E45+F45+G45+H45+I45+J45-K45 -> 0 | O45: =L45-M45-N45 -> 0
H46: =SUM('крейзи консум новый'!C86:C87) -> 0 | I46: =SUM('крейзи консум новый'!X86:X87) -> 0 | J46: =SUM('Общий чай'!S85:S86) -> 0 | L46: =D46+E46+F46+G46+H46+I46+J46-K46 -> 0 | O46: =L46-M46-N46 -> 0
H47: =SUM('крейзи консум новый'!C88:C89) -> 0 | I47: =SUM('крейзи консум новый'!X88:X89) -> 0 | J47: =SUM('Общий чай'!S87:S88) -> 0 | L47: =D47+E47+F47+G47+H47+I47+J47-K47 -> 0 | O47: =L47-M47-N47 -> 0
H48: =SUM('крейзи консум новый'!C90:C91) -> 0 | I48: =SUM('крейзи консум новый'!X90:X91) -> 0 | J48: =SUM('Общий чай'!S89:S90) -> 0 | L48: =D48+E48+F48+G48+H48+I48+J48-K48 -> 0 | O48: =L48-M48-N48 -> 0
A49: Р | B49: 1 | C49: Дима | H49: =SUM('крейзи консум новый'!C92:C93) -> 0 | I49: =SUM('крейзи консум новый'!X92:X93) -> 0 | J49: =SUM('Общий чай'!S91:S92) -> 2500 | L49: =D49+E49+F49+G49+H49+I49+J49-K49 -> 2500 | M49: 2500 | O49: =L49-M49-N49 -> 0
A50: Р | B50: 17 | C50: Ильяз | H50: =SUM('крейзи консум новый'!C94:C95) -> 0 | I50: =SUM('крейзи консум новый'!X94:X95) -> 0 | J50: =SUM('Общий чай'!S93:S94) -> 3500 | L50: =D50+E50+F50+G50+H50+I50+J50-K50 -> 3500 | M50: 3500 | O50: =L50-M50-N50 -> 0
A51: Р | B51: 15 | C51: Гриша | H51: =SUM('крейзи консум новый'!C96:C97) -> 0 | I51: =SUM('крейзи консум новый'!X96:X97) -> 0 | J51: =SUM('Общий чай'!S95:S96) -> 1000 | L51: =D51+E51+F51+G51+H51+I51+J51-K51 -> 1000 | M51: 1000 | O51: =L51-M51-N51 -> 0
A52: Б | B52: 4 | C52: Камила | D52: 3500 | F52: 500 | H52: =SUM('крейзи консум новый'!C99:C100) -> 0 | I52: =SUM('крейзи консум новый'!X99:X100) -> 600 | J52: =SUM('Общий чай'!S98:S99) -> 1000 | L52: =SUM(D52:J52)-K52 -> 5600 | M52: 1600 | N52: 4000 | O52: =L52-M52-N52 -> 0
A53: Б | B53: 52 | C53: Даня | D53: 3500 | F53: 500 | H53: =SUM('крейзи консум новый'!C101:C102) -> 0 | I53: =SUM('крейзи консум новый'!X101:X102) -> 0 | J53: =SUM('Общий чай'!S100:S101) -> 3000 | L53: =SUM(D53:J53)-K53 -> 7000 | M53: 3000 | N53: 4000 | O53: =L53-M53-N53 -> 0
A54: Б | H54: =SUM('крейзи консум новый'!C103:C104) -> 0 | I54: =SUM('крейзи консум новый'!X103:X104) -> 0 | J54: =SUM('Общий чай'!S102:S103) -> 0 | L54: =SUM(D54:J54)-K54 -> 0 | O54: =L54-M54-N54 -> 0
A55: Б | H55: =SUM('крейзи консум новый'!C105:C106) -> 0 | I55: =SUM('крейзи консум новый'!X105:X106) -> 0 | J55: =SUM('Общий чай'!S104:S105) -> 0 | L55: =SUM(D55:J55)-K55 -> 0 | O55: =L55-M55-N55 -> 0
A56: К | B56: 21 | C56: Маратик | H56: =SUM('крейзи консум новый'!C107:C108) -> 0 | I56: =SUM('крейзи консум новый'!X107:X108) -> 10400 | J56: =SUM('Общий чай'!S106:S107) -> 2000 | L56: =SUM(D56:J56)-K56 -> 12400 | M56: 4700 | N56: 7700 | O56: =L56-M56-N56 -> 0
A57: К | H57: =SUM('крейзи консум новый'!C109:C110) -> 0 | I57: =SUM('крейзи консум новый'!X109:X110) -> 0 | J57: =SUM('Общий чай'!S108:S109) -> 0 | L57: =SUM(D57:J57)-K57 -> 0 | O57: =L57-M57-N57 -> 0
A58: Dj | B58: 14 | C58: Сергей | D58: 3000 | H58: =SUM('крейзи консум новый'!C111:C112) -> 0 | I58: =SUM('крейзи консум новый'!X111:X112) -> 0 | J58: =SUM('Общий чай'!S110:S111) -> 4200 | L58: =SUM(D58:J58)-K58 -> 7200 | M58: 3000 | N58: 4200 | O58: =L58-M58-N58 -> 0
A59: М | B59: 69 | C59: Марина | D59: 4000 | F59: 150 | H59: =SUM('крейзи консум новый'!C113:C114) -> 0 | I59: =SUM('крейзи консум новый'!X113:X114) -> 0 | J59: =SUM('Общий чай'!S112:S113) -> 6350 | L59: =SUM(D59:J59)-K59 -> 10500 | M59: 5850 | O59: =L59-M59-N59 -> 4650
A60: А | B60: 17 | C60: Юля | D60: 15000 | H60: =SUM('крейзи консум новый'!C115:C116) -> 0 | I60: =SUM('крейзи консум новый'!X115:X116) -> 0 | J60: 16550 | L60: =SUM(D60:J60)-K60 -> 31550 | M60: 14850 | N60: 16700 | O60: =L60-M60-N60 -> 0
A61: А | H61: =SUM('крейзи консум новый'!C117:C118) -> 0 | I61: =SUM('крейзи консум новый'!X117:X118) -> 0 | J61: =SUM('Общий чай'!S116:S117) -> 0 | L61: =SUM(D61:J61)-K61 -> 0 | O61: =L61-M61-N61 -> 0
A62: Лм | H62: =SUM('крейзи консум новый'!C119:C120) -> 0 | I62: =SUM('крейзи консум новый'!X119:X120) -> 0 | J62: =SUM('Общий чай'!S118:S119)*0.5 -> 0 | L62: =SUM(D62:J62)-K62 -> 0 | O62: =L62-M62-N62 -> 0
A63: Лм | H63: =SUM('крейзи консум новый'!C121:C122) -> 0 | I63: =SUM('крейзи консум новый'!X121:X122) -> 0 | J63: =SUM('Общий чай'!S120:S121)*0.5 -> 0 | L63: =SUM(D63:J63)-K63 -> 0 | O63: =L63-M63-N63 -> 0
A64: СБ | C64: Женя Егоров | D64: 4000 | G64: 2700 | H64: =SUM('крейзи консум новый'!C123:C124) -> 0 | I64: =SUM('крейзи консум новый'!X123:X124) -> 0 | J64: =SUM('Общий чай'!S122:S123) -> 1600 | L64: =D64+G64+H64+I64+J64-K64 -> 8300 | M64: 2950 | N64: 350 | O64: =L64-M64-N64 -> 5000 | P64: (вход-1350-бн)
A65: СБ | C65: Дима Песков | D65: 4000 | G65: 2650 | H65: =SUM('крейзи консум новый'!C125:C126) -> 0 | I65: =SUM('крейзи консум новый'!X125:X126) -> 0 | J65: =SUM('Общий чай'!S124:S125) -> 1600 | L65: =D65+G65+H65+I65+J65-K65 -> 8250 | M65: 2900 | N65: 350 | O65: =L65-M65-N65 -> 5000 | P65: (вход-1300 бн)
A66: СБ | C66: Денис Ермаков | D66: 4000 | G66: 2650 | H66: =SUM('крейзи консум новый'!C127:C128) -> 0 | I66: =SUM('крейзи консум новый'!X127:X128) -> 0 | J66: =SUM('Общий чай'!S125:S126) -> 1650 | L66: =D66+G66+H66+I66+J66-K66 -> 8300 | M66: 3000 | N66: 300 | O66: =L66-M66-N66 -> 5000 | P66: (вход-1350 бн)
C67: уборщица | D67: 2000 | L67: =D67+G67+H67+I67+J67-K67 -> 2000 | O67: =L67-M67-N67 -> 2000
A68: ИТОГО | D68: =SUM(D2:D67) -> 61500 | E68: =SUM(E3:E67) -> 0 | F68: =SUM(F19:F65) -> 5950 | G68: =SUM(G2:G67) -> 8000 | H68: =SUM(H2:H67) -> 108600 | I68: =SUM(I2:I67) -> 21900 | J68: =SUM(J2:J67) -> 68450 | K68: =SUM(K2:K67) -> 0 | L68: =SUM(L2:L67) -> 274400 | M68: =SUM(M2:M67) -> 169750 | N68: =SUM(N2:N67) -> 73000 | O68: =SUM(O2:O67) -> 31650
C69: промоутеры | D69: 50500 | N69: =SUM(D69) -> 50500
C70: такси вход | O70: =SUM(D70:N70) -> 0
C71: % таксистам | O71: =SUM(D71:N71) -> 0
C72: прочие расходы | O72: =SUM(D72:N72) -> 0
C73: 5 % промоутера Р9 | D73: 300 | N73: =SUM(D73) -> 300
C74: стилисты/визажисты | D74: 1000 | N74: =SUM(D74) -> 1000
C75: 5 % промоутеров | D75: 11100 | N75: =SUM(D75) -> 11100
C76: % Жени | N76: =SUM(D76) -> 0
O77: =SUM(D77:N77) -> 0
O78: =SUM(D78:N78) -> 0 | P78: инкассация:
A79: НАЛ: | C79: 125550 | K79: =SUM(K68:K78) -> 0 | L79: =SUM(L68:L78) -> 274400 | M79: =SUM(M68:M78) -> 169750 | N79: =SUM(N68:N78) -> 135900 | O79: =SUM(O68:O78) -> 31650 | P79: =$C$79-$O$79 -> 93900

Sheet крейзи консум новый
A1: ДАТА | K1: АДМИНИСТРАТОР
A2: № | C2: СУММА CRAZY | D2: ПОЗИЦИИ ПО CRAZY | X2: СУММА КОНСУМАЦИИ | Y2: ПОЗИЦИИ ПО КОНСУМАЦИИ
A3: Танцовщицы | Y3: Танцовщицы
A4: Д | B4: =SUM('Лист выплат'!B3) -> 3 | C4: =SUM(D4:W4) -> 5375 | D4: 1250 | E4: 1000 | F4: 2000 | G4: 1125 | X4: =SUM(Y4:AR4) -> 1200 | Y4: 600 | Z4: 600
D5: л26 | E5: л27 | F5: л28 | G5: Л26 | Y5: со4 | Z5: со4 | AT5: ЛАЙФ-60%
A6: Д | B6: =SUM('Лист выплат'!B4) -> 5 | C6: =SUM(D6:W6) -> 16200 | D6: 1125 | E6: 900 | F6: 1800 | G6: 4050 | H6: 2700 | I6: 1800 | J6: 1125 | K6: 900 | L6: 1800 | X6: =SUM(Y6:AR6) -> 3800 | Y6: 3200 | Z6: 600
D7: Л26 | E7: Л27 | F7: Л28 | G7: л25 | H7: л33 | I7: л34 | J7: Л26 | K7: Л27 | L7: Л28 | Y7: в4 | Z7: со4
A8: Д | B8: =SUM('Лист выплат'!B5) -> 9 | C8: =SUM(D8:W8) -> 8550 | D8: 4050 | E8: 2700 | F8: 1800 | X8: =SUM(Y8:AR8) -> 300 | Y8: 300
D9: л25 | E9: л33 | F9: л34 | Y9: со1
A10: Д | B10: =SUM('Лист выплат'!B6) -> 11 | C10: =SUM(D10:W10) -> 20450 | D10: 1125 | E10: 900 | F10: 1800 | G10: 1250 | H10: 1000 | I10: 2000 | J10: 1125 | K10: 900 | L10: 1800 | M10: 4050 | N10: 2700 | O10: 1800 | X10: =SUM(Y10:AR10) -> 600 | Y10: 600
D11: Л26 | E11: Л27 | F11: Л28 | G11: л26 | H11: л27 | I11: л28 | J11: Л26 | K11: Л27 | L11: Л28 | M11: л25 | N11: л33 | O11: л34 | Y11: со4
A12: Д | B12: =SUM('Лист выплат'!B7) -> 18 | C12: =SUM(D12:W12) -> 34200 | D12: 4050 | E12: 2700 | F12: 1800 | G12: 4050 | H12: 2700 | I12: 1800 | J12: 4050 | K12: 2700 | L12: 1800 | M12: 4050 | N12: 2700 | O12: 1800 | X12: =SUM(Y12:AR12) -> 0
D13: л25 | E13: л33 | F13: л34 | G13: л25 | H13: л33 | I13: л34 | J13: л25 | K13: л33 | L13: л34 | M13: л25 | N13: л33 | O13: л34
A14: Д | B14: =SUM('Лист выплат'!B8) -> 21 | C14: =SUM(D14:W14) -> 0 | X14: =SUM(Y14:AR14) -> 2280 | Y14: 300 | Z14: 300 | AA14: 600 | AB14: 540 | AC14: 540
Y15: со1 | Z15: со1 | AA15: со4 | AB15: со4 | AC15: со4
A16: Д | B16: =SUM('Лист выплат'!B9) -> 66 | C16: =SUM(D16:W16) -> 23850 | D16: 1125 | E16: 900 | F16: 1800 | G16: 1125 | H16: 900 | I16: 1800 | J16: 4050 | K16: 2700 | L16: 1800 | M16: 1125 | N16: 900 | O16: 1800 | P16: 1125 | Q16: 900 | R16: 1800 | X16: =SUM(Y16:AR16) -> 1740 | Y16: 600 | Z16: 600 | AA16: 540
D17: Л26 | E17: Л27 | F17: Л28 | G17: Л26 | H17: Л27 | I17: Л28 | J17: л25 | K17: л33 | L17: л34 | M17: Л26 | N17: Л27 | O17: Л28 | P17: Л26 | Q17: Л27 | R17: Л28 | Y17: со4 | Z17: со4 | AA17: со4
A18: Д | B18: =SUM('Лист выплат'!B10) -> 0 | C18: =SUM(D18:W18) -> 0 | X18: =SUM(Y18:AR18) -> 0
A20: Д | B20: =SUM('Лист выплат'!B11) -> 0 | C20: =SUM(D20:W20) -> 0 | X20: =SUM(Y20:AR20) -> 0
A22: Д | B22: =SUM('Лист выплат'!B12) -> 0 | C22: =SUM(D22:W22) -> 0 | X22: =SUM(Y22:AR22) -> 0
A24: Д | B24: =SUM('Лист выплат'!B13) -> 0 | C24: =SUM(D24:W24) -> 0 | X24: =SUM(Y24:AR24) -> 0
A26: Д | B26: =SUM('Лист выплат'!B14) -> 0 | C26: =SUM(D26:W26) -> 0 | X26: =SUM(Y26:AR26) -> 0
A28: Д | B28: =SUM('Лист выплат'!B15) -> 0 | C28: =SUM(D28:W28) -> 0 | X28: =SUM(Y28:AR28) -> 0
A30: Д | B30: =SUM('Лист выплат'!B16) -> 0 | C30: =SUM(D30:W30) -> 0 | X30: =SUM(Y30:AR30) -> 0
A32: Д | B32: =SUM('Лист выплат'!B17) -> 0 | C32: =SUM(D32:W32) -> 0 | X32: =SUM(Y32:AR32) -> 0
A34: Патигерл | Y34: Патигерл
A35: Г | B35: =SUM('Лист выплат'!B19) -> 0 | C35: =SUM(D35:W35) -> 0 | X35: =SUM(Y35:AR35) -> 0
A37: Г | B37: =SUM('Лист выплат'!B20) -> 0 | C37: =SUM(D37:W37) -> 0 | X37: =SUM(Y37:AR37) -> 0
A39: Г | B39: =SUM('Лист выплат'!B21) -> 0 | C39: =SUM(D39:W39) -> 0 | X39: =SUM(Y39:AR39) -> 0
A41: Г | B41: =SUM('Лист выплат'!B22) -> 0 | C41: =SUM(D41:W41) -> 0 | X41: =SUM(Y41:AR41) -> 0
A43: Г | B43: =SUM('Лист выплат'!B23) -> 0 | C43: =SUM(D43:W43) -> 0 | X43: =SUM(Y43:AR43) -> 0
A45: Г | B45: =SUM('Лист выплат'!B24) -> 0 | C45: =SUM(D45:W45) -> 0 | X45: =SUM(Y45:AR45) -> 0
A47: Г | B47: =SUM('Лист выплат'!B25) -> 0 | C47: =SUM(D47:W47) -> 0 | X47: =SUM(Y47:AR47) -> 0
A49: Г | B49: =SUM('Лист выплат'!B26) -> 0 | C49: =SUM(D49:W49) -> 0 | X49: =SUM(Y49:AR49) -> 0
A51: Г | B51: =SUM('Лист выплат'!B27) -> 0 | C51: =SUM(D51:W51) -> 0 | X51: =SUM(Y51:AR51) -> 0
A53: Г | B53: =SUM('Лист выплат'!B28) -> 0 | C53: =SUM(D53:W53) -> 0 | X53: =SUM(Y53:AR53) -> 0
B55: Официанты | Y55: Официанты
A56: Оф | B56: =SUM('Лист выплат'!B30) -> 3 | C56: =SUM(D56:W56) -> 0 | X56: =SUM(Y56:AR56) -> 1080 | Y56: 540 | Z56: 540
Y57: со4 | Z57: со4
A58: Оф | B58: =SUM('Лист выплат'!B31) -> 4 | C58: =SUM(D58:W58) -> 0 | X58: =SUM(Y58:AR58) -> 0
A60: Оф | B60: =SUM('Лист выплат'!B32) -> 0 | C60: =SUM(D60:W60) -> 0 | X60: =SUM(Y60:AR60) -> 0
A62: Оф | B62: =SUM('Лист выплат'!B33) -> 0 | C62: =SUM(D62:W62) -> 0 | X62: =SUM(Y62:AR62) -> 0
A64: Оф | B64: =SUM('Лист выплат'!B34) -> 0 | C64: =SUM(D64:W64) -> 0 | X64: =SUM(Y64:AR64) -> 0
A66: Оф | B66: =SUM('Лист выплат'!B35) -> 0 | C66: =SUM(D66:W66) -> 0 | X66: =SUM(Y66:AR66) -> 0
A68: Оф | B68: =SUM('Лист выплат'!B36) -> 0 | C68: =SUM(D68:W68) -> 0 | X68: =SUM(Y68:AR68) -> 0
A70: Оф | B70: =SUM('Лист выплат'!B37) -> 0 | C70: =SUM(D70:W70) -> 0 | X70: =SUM(Y70:AR70) -> 0
B72: Хостес | X72: Хостес
A73: Н | B73: =SUM('Лист выплат'!B39) -> 3 | C73: =SUM(D73:W73) -> 0 | X73: =SUM(Y73:AR73) -> 0
A75: Н | B75: =SUM('Лист выплат'!B40) -> 4 | C75: =SUM(D75:W75) -> 0 | X75: =SUM(Y75:AR75) -> 0
A77: Н | B77: =SUM('Лист выплат'!B41) -> 0 | C77: =SUM(D77:W77) -> 0 | X77: =SUM(Y77:AR77) -> 0
A79: Н | B79: =SUM('Лист выплат'!B42) -> 0 | C79: =SUM(D79:W79) -> 0 | X79: =SUM(Y79:AR79) -> 0
A81: Н | B81: =SUM('Лист выплат'!B43) -> 0 | C81: =SUM(D81:W81) -> 0 | X81: =SUM(Y81:AR81) -> 0
B83: Стажеры | X83: Стажеры
B84: =SUM('Лист выплат'!B45) -> 0 | C84: =SUM(D84:W84) -> 0 | X84: =SUM(Y84:AR84) -> 0
B86: =SUM('Лист выплат'!B46) -> 0 | C86: =SUM(D86:W86) -> 0 | X86: =SUM(Y86:AR86) -> 0
A88: 0 | B88: =SUM('Лист выплат'!B47) -> 0 | C88: =SUM(D88:W88) -> 0 | X88: =SUM(Y88:AR88) -> 0
A90: =SUM('Лист выплат'!A48) -> 0 | B90: =SUM('Лист выплат'!B48) -> 0 | C90: =SUM(D90:W90) -> 0 | X90: =SUM(Y90:AR90) -> 0
A92: =SUM('Лист выплат'!A49) -> 0 | B92: =SUM('Лист выплат'!B49) -> 1 | C92: =SUM(D92:W92) -> 0 | X92: =SUM(Y92:AR92) -> 0
A94: =SUM('Лист выплат'!A50) -> 0 | B94: =SUM('Лист выплат'!B50) -> 17 | C94: =SUM(D94:W94) -> 0 | X94: =SUM(Y94:AR94) -> 0
A96: =SUM('Лист выплат'!A51) -> 0 | B96: =SUM('Лист выплат'!B51) -> 15 | C96: =SUM(D96:W96) -> 0 | X96: =SUM(Y96:AR96) -> 0
A98: Бар | X98: Бар
A99: Б | B99: =SUM('Лист выплат'!B52) -> 4 | C99: =SUM(D99:W99) -> 0 | X99: =SUM(Y99:AR99) -> 600 | Y99: 600
Y100: со4
A101: Б | B101: =SUM('Лист выплат'!B53) -> 52 | C101: =SUM(D101:W101) -> 0 | X101: =SUM(Y101:AR101) -> 0
A103: Б | B103: =SUM('Лист выплат'!B54) -> 0 | C103: =SUM(D103:W103) -> 0 | X103: =SUM(Y103:AR103) -> 0
A105: Б | B105: =SUM('Лист выплат'!B55) -> 0 | C105: =SUM(D105:W105) -> 0 | X105: =SUM(Y105:AR105) -> 0
A107: К | B107: =SUM('Лист выплат'!B56) -> 21 | C107: =SUM(D107:W107) -> 0 | X107: =SUM(Y107:AR107) -> 10400 | Y107: 900 | Z107: 500 | AA107: 900 | AB107: 900 | AC107: 500 | AD107: 900 | AE107: 500 | AF107: 900 | AG107: 1200 | AH107: 500 | AI107: 900 | AJ107: 900 | AK107: 900
Y108: к1 | Z108: т | AA108: к1 | AB108: к1 | AC108: т | AD108: к1 | AE108: т | AF108: к1 | AG108: к2 | AH108: т | AI108: к1 | AJ108: к1 | AK108: к1
A109: К | B109: =SUM('Лист выплат'!B57) -> 0 | C109: =SUM(D109:W109) -> 0 | X109: =SUM(Y109:AR109) -> 0
A111: Dj | B111: =SUM('Лист выплат'!B58) -> 14 | C111: =SUM(D111:W111) -> 0 | X111: =SUM(Y111:AR111) -> 0
A113: М | B113: =SUM('Лист выплат'!B59) -> 69 | C113: =SUM(D113:W113) -> 0 | X113: =SUM(Y113:AR113) -> 0
A115: А | B115: =SUM('Лист выплат'!B60) -> 17 | C115: =SUM(D115:W115) -> 0 | X115: =SUM(Y115:AR115) -> 0
A117: А | B117: =SUM('Лист выплат'!B61) -> 0 | C117: =SUM(D117:W117) -> 0 | X117: =SUM(Y117:AR117) -> 0
A119: Лм | B119: =SUM('Лист выплат'!B62) -> 0 | C119: =SUM(D119:W119) -> 0 | X119: =SUM(Y119:AR119) -> 0
A121: Лм | B121: =SUM('Лист выплат'!B63) -> 0 | C121: =SUM(D121:W121) -> 0 | X121: =SUM(Y121:AR121) -> 0
A123: СБ | B123: =SUM('Лист выплат'!B65) -> 0 | C123: =SUM(D123:W123) -> 0 | X123: =SUM(Y123:AR123) -> 0
A125: СБ | B125: =SUM('Лист выплат'!B67) -> 0 | C125: =SUM(D125:W125) -> 0 | X125: =SUM(Y125:AR125) -> 0
A127: СБ | B127: =SUM('Лист выплат'!B69) -> 0 | C127: =SUM(D127:W127) -> 0 | X127: =SUM(Y127:AR127) -> 0
C129: ='Лист выплат'!H68 -> 108600 | X129: =SUM('Лист выплат'!I68) -> 21900

Sheet Общий чай
A1: CARTEL | F1: ДАТА: | H1: АДМИНИСТРАТОР: | M1: ВЕДОМОСТЬ ПО ОБЩЕМУ ЧАЮ | S1: Итого:
A2: Танцовщицы
A3: Д | B3: =SUM('Лист выплат'!B3) -> 3 | S3: =SUM(C3:R4) -> 0
A5: Д | B5: =SUM('Лист выплат'!B4) -> 5 | C5: 1000 | D5: 500 | E5: 3000 | F5: 500 | S5: =SUM(C5:R6) -> 5000
A7: Д | B7: =SUM('Лист выплат'!B5) -> 9 | S7: =SUM(C7:R8) -> 0
A9: Д | B9: =SUM('Лист выплат'!B6) -> 11 | C9: 1000 | D9: 3000 | E9: 2000 | F9: 1000 | S9: =SUM(C9:R10) -> 7000
A11: Д | B11: =SUM('Лист выплат'!B7) -> 18 | C11: 1000 | S11: =SUM(C11:R12) -> 1000
A13: Д | B13: =SUM('Лист выплат'!B8) -> 21 | C13: 1000 | D13: 2500 | E13: 1000 | F13: 5000 | S13: =SUM(C13:R14) -> 9500
A15: Д | B15: =SUM('Лист выплат'!B9) -> 66 | C15: 1000 | D15: 1000 | E15: 500 | F15: 2000 | G15: 2500 | H15: 1000 | I15: 4000 | J15: 2000 | S15: =SUM(C15:R16) -> 14000
A17: Д | B17: =SUM('Лист выплат'!B10) -> 0 | S17: =SUM(C17:R18) -> 0
A19: Д | B19: =SUM('Лист выплат'!B11) -> 0 | S19: =SUM(C19:R20) -> 0
A21: Д | B21: =SUM('Лист выплат'!B12) -> 0 | S21: =SUM(C21:R22) -> 0
A23: Д | B23: =SUM('Лист выплат'!B13) -> 0 | S23: =SUM(C23:R24) -> 0
A25: Д | B25: =SUM('Лист выплат'!B13) -> 0 | S25: =SUM(C25:R26) -> 0
A27: Д | B27: =SUM('Лист выплат'!B15) -> 0 | S27: =SUM(C27:R28) -> 0
A29: Д | B29: =SUM('Лист выплат'!B16) -> 0 | S29: =SUM(C29:R30) -> 0
A31: Д | B31: =SUM('Лист выплат'!B17) -> 0 | S31: =SUM(C31:R32) -> 0
A33: Патигерл
A34: Г | B34: =SUM('Лист выплат'!B19) -> 0 | S34: =SUM(C34:R35) -> 0
A36: Г | B36: =SUM('Лист выплат'!B20) -> 0 | S36: =SUM(C36:R37) -> 0
A38: Г | B38: =SUM('Лист выплат'!B21) -> 0 | S38: =SUM(C38:R39) -> 0
A40: Г | B40: =SUM('Лист выплат'!B22) -> 0 | S40: =SUM(C40:R41) -> 0
A42: Г | B42: =SUM('Лист выплат'!B23) -> 0 | S42: =SUM(C42:R43) -> 0
A44: Г | B44: =SUM('Лист выплат'!B24) -> 0 | S44: =SUM(C44:R45) -> 0
A46: Г | B46: =SUM('Лист выплат'!B25) -> 0 | S46: =SUM(C46:R47) -> 0
A48: Г | B48: =SUM('Лист выплат'!B26) -> 0 | S48: =SUM(C48:R49) -> 0
A50: Г | B50: =SUM('Лист выплат'!B27) -> 0 | S50: =SUM(C50:R51) -> 0
A52: Г | B52: =SUM('Лист выплат'!B28) -> 0 | S52: =SUM(C52:R53) -> 0
A54: Официанты
A55: Оф | B55: =SUM('Лист выплат'!B30) -> 3 | C55: 2000 | D55: 1000 | S55: =SUM(C55:R56) -> 3000
A57: Оф | B57: =SUM('Лист выплат'!B31) -> 4 | C57: 1000 | D57: 1500 | S57: =SUM(C57:R58) -> 2500
A59: Оф | B59: =SUM('Лист выплат'!B32) -> 0 | S59: =SUM(C59:R60) -> 0
A61: Оф | B61: =SUM('Лист выплат'!B33) -> 0 | S61: =SUM(C61:R62) -> 0
A63: Оф | B63: =SUM('Лист выплат'!B34) -> 0 | S63: =SUM(C63:R64) -> 0
A65: Оф | B65: =SUM('Лист выплат'!B35) -> 0 | S65: =SUM(C65:R66) -> 0
A67: Оф | B67: =SUM('Лист выплат'!B36) -> 0 | S67: =SUM(C67:R68) -> 0
A69: Оф | B69: =SUM('Лист выплат'!B37) -> 0 | S69: =SUM(C69:R70) -> 0
A71: Хостес
A72: Н | B72: =SUM('Лист выплат'!B39) -> 3 | C72: 500 | D72: 500 | S72: =SUM(C72:R73) -> 1000
A74: Н | B74: =SUM('Лист выплат'!B40) -> 4 | C74: 500 | D74: 1000 | S74: =SUM(C74:R75) -> 1500
A76: Н | B76: =SUM('Лист выплат'!B41) -> 0 | S76: =SUM(C76:R77) -> 0
A78: Н | B78: =SUM('Лист выплат'!B42) -> 0 | S78: =SUM(C78:R79) -> 0
A80: Н | B80: =SUM('Лист выплат'!B43) -> 0 | S80: =SUM(C80:R81) -> 0
A82: Стажеры
B83: =SUM('Лист выплат'!B45) -> 0 | S83: =SUM(C83:R84) -> 0
B85: =SUM('Лист выплат'!B46) -> 0 | S85: =SUM(C85:R86) -> 0
A87: 0 | B87: =SUM('Лист выплат'!B47) -> 0 | S87: =SUM(C87:R88) -> 0
A89: 0 | B89: =SUM('Лист выплат'!B48) -> 0 | S89: =SUM(C89:R90) -> 0
A91: 0 | B91: =SUM('Лист выплат'!B49) -> 1 | C91: 2500 | S91: =SUM(C91:R92) -> 2500
A93: 0 | B93: =SUM('Лист выплат'!B50) -> 17 | C93: 3500 | S93: =SUM(C93:R94) -> 3500
A95: 0 | B95: =SUM('Лист выплат'!B51) -> 15 | C95: 1000 | S95: =SUM(C95:R96) -> 1000
A97: Бар
A98: Б | B98: =SUM('Лист выплат'!B52) -> 4 | C98: 1000 | S98: =SUM(C98:R99) -> 1000
A100: Б | B100: =SUM('Лист выплат'!B53) -> 52 | C100: 500 | D100: 500 | E100: 500 | F100: 500 | G100: 500 | H100: 500 | S100: =SUM(C100:R101) -> 3000
A102: Б | B102: =SUM('Лист выплат'!B54) -> 0 | S102: =SUM(C102:R103) -> 0
A104: Б | B104: =SUM('Лист выплат'!B55) -> 0 | S104: =SUM(C104:R105) -> 0
A106: К | B106: =SUM('Лист выплат'!B56) -> 21 | C106: 500 | D106: 500 | E106: 500 | F106: 500 | S106: =SUM(C106:R107) -> 2000
A108: К | B108: =SUM('Лист выплат'!B57) -> 0 | S108: =SUM(C108:R109) -> 0
A110: Dj | B110: =SUM('Лист выплат'!B58) -> 14 | C110: 500 | D110: 500 | E110: 500 | F110: 500 | G110: 1000 | H110: 200 | I110: 500 | J110: 500 | S110: =SUM(C110:R111) -> 4200
A112: М | B112: =SUM('Лист выплат'!B59) -> 69 | C112: 500 | D112: 500 | E112: 1000 | F112: 500 | G112: 500 | H112: 500 | I112: 500 | J112: 500 | K112: 500 | L112: 500 | M112: 350 | N112: 500 | S112: =SUM(C112:R113) -> 6350
A114: А | B114: =SUM('Лист выплат'!B60) -> 17 | C114: 500 | D114: 500 | E114: 1000 | F114: 1500 | G114: 7000 | H114: 1000 | I114: 3000 | J114: 2000 | K114: 900 | L114: 1000 | M114: 1500 | N114: 1500 | O114: 1700 | S114: =SUM(C114:R115) -> 23100
A116: А | B116: =SUM('Лист выплат'!B61) -> 0 | S116: =SUM(C116:R117) -> 0
A118: Лм | B118: =SUM('Лист выплат'!B62) -> 0 | S118: =SUM(C118:R119) -> 0
A120: Лм | B120: =SUM('Лист выплат'!B63) -> 0 | S120: =SUM(C120:R121) -> 0
A122: СБ | B122: =SUM('Лист выплат'!B64) -> 0 | C122: 500 | D122: 500 | E122: 500 | F122: 100 | S122: =SUM(C122:R123) -> 1600
A124: СБ | B124: =SUM('Лист выплат'!B65) -> 0 | C124: 500 | D124: 500 | E124: 500 | F124: 100 | S124: =SUM(C124:R125) -> 1600
A126: СБ | B126: =SUM('Лист выплат'!B66) -> 0 | C126: 500 | D126: 500 | E126: 500 | F126: 150 | S126: =SUM(C126:R127) -> 1650
S128: =SUM(C128:R129) -> 0
S130: =SUM(C130:R131) -> 0
S132: =SUM(C132:R133) -> 0
S134: =SUM(C134:R135) -> 0
B136: CLUB | S136: =SUM(C136:R137) -> 0
B139: ИТОГО ПО ТАНЦОВЩИЦАМ: | F139: =SUM(S3:S32) -> 36500 | I139: ИТОГО ПО ПЕРСОНАЛУ: | M139: =SUM(S34:S119,S120:S135) -> 59500 | P139: ИТОГО ОБЩЕЕ: | R139: =SUM(F139,M139) -> 96000

Sheet Штрафы
D1: ВЕДОМОСТЬ ПО ШТРАФАМ
A3: CARTEL | C3: ДАТА: | D3: АДМИНИСТРАТОР:
A5: № | B5: ФИО и ДОЛЖНОСТЬ | C5: ПРИЧИНА ШТРАФА | D5: СУММА | E5: ПОДПИСЬ ОШТРАФОВАННОГО
D20: ИТОГО:
A21: Подпись АДМИНИСТРАТОРА:

Sheet Промоутеры
A1: Дата: 01.11 Админ:
A3: № | B3: Имя | C3: Ставка | D3: Гостей за смену | F3: Сумма общая | G3: Штраф | H3: К выплате | I3: Остаток
D4: кол-во | E4: сумма
A5: Р1 | B5: Дима | C5: 1000 | D5: 5.5 | E5: 12000 | F5: =SUM(C5,E5) -> 13000 | I5: =F5-G5-H5 -> 13000
A6: Р9 | B6: Рома | C6: 1000 | D6: 2 | E6: 4000 | F6: =SUM(C6,E6) -> 5000 | I6: =F6-G6-H6 -> 5000
A7: Р10 | B7: Дима | C7: 1000 | F7: =SUM(C7,E7) -> 1000 | I7: =F7-G7-H7 -> 1000
A8: Р15 | B8: Гриша | C8: 1000 | D8: 4.5 | E8: 9000 | F8: =SUM(C8,E8) -> 10000 | I8: =F8-G8-H8 -> 10000
A9: Р17 | B9: Ильяз | C9: 1000 | D9: 11 | E9: 19500 | F9: =SUM(C9,E9) -> 20500 | I9: =F9-G9-H9 -> 20500
A10: Р29 | B10: Сергей | C10: 1000 | F10: =SUM(C10,E10) -> 1000 | I10: =F10-G10-H10 -> 1000
F11: =SUM(C11,E11) -> 0 | I11: =F11-G11-H11 -> 0
F12: =SUM(C12,E12) -> 0 | I12: =F12-G12-H12 -> 0
F13: =SUM(C13,E13) -> 0 | I13: =F13-G13-H13 -> 0
F14: =SUM(F5:F13) -> 50500 | I14: =SUM(I5:I13) -> 50500

Sheet Расчетный Карты
A1: Дата: | K1: Управляющий: | AI1: Ведомость Консумационных Карт
A3: № Карты | C3: Сумма Общего Чека | H3: Кол-во Человек | M3: № Карты | O3: Сумма Общего Чека | T3: Кол-во Человек | Y3: № Карты | AA3: Сумма Общего Чека | AF3: Кол-во Человек
A44: Примечание:
AF50: подпись

Sheet Доходы сотрудников
D1: ДАТА: 01.11 | N1: АДМИНИСТРАТОР: А17
B3: № | C3: ФАМИЛИЯ | D3: СТАВКА | E3: 5% ЛМ | F3: 0.05 | G3: ПРОМО | H3: CRAZY MENU | I3: Консумация | J3: ЧАЕВЫЕ | K3: ШТРАФЫ | L3: ИТОГО выплат по смене | M3: ДОЛГ | N3: ДОЛГ НАЛ | O3: ИТОГО К ВЫПЛАТЕ | P3: ПОДПИСЬ РАБОТНИКА
B4: Д3 | C4: Даша
B5: Д5 | C5: Софья
B6: Д9 | C6: Лилит
B7: Д11 | C7: Дана
B8: Д18 | C8: Аннет
B9: Д21 | C9: Банни
B10: Д66 | C10: Алиса
B11: Д6 | C11: Саманта
B13: Оф3 | C13: Каталина
B14: Оф4 | C14: Ника
B16: Н3 | C16: Влада
B17: Н4 | C17: Тати
... B22: К21 | C22: Маратик
B23: Дж14 | C23: Сергей | D23: 3000
B25: М69 | C25: Марина
B26: А17 | C26: Юля
B28: СБ | C28: Женя Егоров | D28: 4000
B29: СБ | C29: Дима Песков | D29: 4000
B30: СБ | C30: Денис Ермаков | D30: 4000
C32: уборщица | D32: 2000
C38: ИТОГО:
B39: Подпись АДМИНИСТРАТОРА:
